LICENSE
MANIFEST.in
README.md
setup.cfg
setup.py
cmsplugin_iframe2/__init__.py
cmsplugin_iframe2/cms_plugins.py
cmsplugin_iframe2/models.py
cmsplugin_iframe2.egg-info/PKG-INFO
cmsplugin_iframe2.egg-info/SOURCES.txt
cmsplugin_iframe2.egg-info/dependency_links.txt
cmsplugin_iframe2.egg-info/requires.txt
cmsplugin_iframe2.egg-info/top_level.txt
cmsplugin_iframe2/conf/__init__.py
cmsplugin_iframe2/conf/default_settings.py
cmsplugin_iframe2/locale/cs/LC_MESSAGES/django.mo
cmsplugin_iframe2/locale/cs/LC_MESSAGES/django.po
cmsplugin_iframe2/migrations/0001_initial.py
cmsplugin_iframe2/migrations/__init__.py
cmsplugin_iframe2/templates/cmsplugin_iframe2/iframe.html